calcalc.py
calcalc/CalCalc.py
calcalc/__init__.py
abeverage_calculator-1.4.dist-info/LICENSE.txt
abeverage_calculator-1.4.dist-info/METADATA
abeverage_calculator-1.4.dist-info/WHEEL
abeverage_calculator-1.4.dist-info/entry_points.txt
abeverage_calculator-1.4.dist-info/top_level.txt
abeverage_calculator-1.4.dist-info/RECORD
