Metadata-Version: 2.1
Name: abeverage-calculator
Version: 1.4
Summary: Evaluate string using python and/or wolfram
Home-page: https://github.com/alizabeverage/python-ay250-homework/tree/main/hw3
Author: Aliza Beverage
Author-email: abeverage@berkeley.edu
License: UNKNOWN
Platform: UNKNOWN
Requires-Python: >=3.6, <4
License-File: LICENSE.txt
Requires-Dist: numexpr
